{"1": {"label": "tan woon yann", "coordinates": {"x": 197, "y": 46, "width": 248, "height": 33}}, "2": {"label": "BOOK TA BHD SDN (TAMAN DAYA)", "coordinates": {"x": 245, "y": 102, "width": 349, "height": 23}}, "3": {"label": "789417-W", "coordinates": {"x": 245, "y": 128, "width": 79, "height": 18}}, "4": {"label": "NO.53 JALAN SAGU 55,57 59, 18,", "coordinates": {"x": 245, "y": 153, "width": 274, "height": 21}}, "5": {"label": "TAMAN DAYA,", "coordinates": {"x": 244, "y": 176, "width": 110, "height": 18}}, "6": {"label": "81100 JOHOR BAHRU,", "coordinates": {"x": 248, "y": 201, "width": 175, "height": 22}}, "7": {"label": "JOHOR.", "coordinates": {"x": 246, "y": 223, "width": 62, "height": 18}}, "8": {"label": "Document TD01167104 No", "coordinates": {"x": 164, "y": 349, "width": 227, "height": 19}}, "9": {"label": "Date 25/12/2018 8:13:39 PM", "coordinates": {"x": 195, "y": 379, "width": 295, "height": 20}}, "10": {"label": "Cashier: MANIS", "coordinates": {"x": 132, "y": 404, "width": 167, "height": 19}}, "11": {"label": "Member:", "coordinates": {"x": 84, "y": 431, "width": 68, "height": 18}}, "12": {"label": "CASH BILL", "coordinates": {"x": 244, "y": 468, "width": 108, "height": 18}}, "13": {"label": "CODE/DESC PRICE AMOUNT Disc", "coordinates": {"x": 235, "y": 514, "width": 414, "height": 20}}, "14": {"label": "QTY RM RM", "coordinates": {"x": 256, "y": 540, "width": 377, "height": 23}}, "15": {"label": "9556939040118 MODELLING KF KIDDY CLAY FISH", "coordinates": {"x": 212, "y": 575, "width": 369, "height": 19}}, "16": {"label": "1PC 9.000 0.00 9.00", "coordinates": {"x": 257, "y": 605, "width": 374, "height": 24}}, "17": {"label": "Total 9.00", "coordinates": {"x": 343, "y": 647, "width": 204, "height": 21}}, "18": {"label": "Rour ding Adjustment: 0.00", "coordinates": {"x": 281, "y": 678, "width": 327, "height": 23}}, "19": {"label": "Round Total 9.00 (RM):", "coordinates": {"x": 265, "y": 713, "width": 358, "height": 26}}, "20": {"label": "Cash 10.00", "coordinates": {"x": 324, "y": 755, "width": 242, "height": 24}}, "21": {"label": "CHANGE 100", "coordinates": {"x": 324, "y": 779, "width": 243, "height": 26}}, "22": {"label": "200", "coordinates": {"x": 365, "y": 801, "width": 79, "height": 56}}, "23": {"label": "GOODS SOLD ARE NOT RE TURNABLEOR", "coordinates": {"x": 246, "y": 850, "width": 305, "height": 18}}, "24": {"label": "EXCHANGEABLE", "coordinates": {"x": 249, "y": 871, "width": 121, "height": 18}}, "25": {"label": "mitti 1551", "coordinates": {"x": 225, "y": 892, "width": 130, "height": 20}}, "26": {"label": "50 it 17, fa", "coordinates": {"x": 235, "y": 911, "width": 202, "height": 19}}, "27": {"label": "THANK YOU", "coordinates": {"x": 247, "y": 950, "width": 92, "height": 18}}, "28": {"label": "PLEASE COFE AGAIN", "coordinates": {"x": 241, "y": 969, "width": 157, "height": 18}}}