{"image": "blank yellow tag.png", "annotations": [{"label": "TAN WOON YANN", "coordinates": {"x": 272.5, "y": 80.5, "width": 257, "height": 38}}, {"label": "YONGFATT ENTERPRISE", "coordinates": {"x": 271.0, "y": 173.5, "width": 278, "height": 26}}, {"label": "(JM0517726)", "coordinates": {"x": 311.0, "y": 214.5, "width": 109, "height": 18}}, {"label": "NO 122.124 JALAN DEDAP 13", "coordinates": {"x": 277.5, "y": 251.5, "width": 243, "height": 17}}, {"label": "81100 JOHOR BAHRU", "coordinates": {"x": 294.0, "y": 283.0, "width": 180, "height": 14}}, {"label": "TEL 07-3523888", "coordinates": {"x": 304.5, "y": 339.0, "width": 138, "height": 18}}, {"label": "GST ID: 000849813504", "coordinates": {"x": 295.0, "y": 386.5, "width": 185, "height": 17}}, {"label": "SIMPLIFIED TAX INVOICE", "coordinates": {"x": 286.5, "y": 425.0, "width": 237, "height": 19}}, {"label": "CASH", "coordinates": {"x": 51.0, "y": 482.5, "width": 48, "height": 17}}, {"label": "DOC NO", "coordinates": {"x": 58.0, "y": 523.0, "width": 59, "height": 17}}, {"label": "CS00031663", "coordinates": {"x": 266.5, "y": 516.0, "width": 110, "height": 21}}, {"label": "DATE", "coordinates": {"x": 432.0, "y": 520.5, "width": 36, "height": 18}}, {"label": "25/12/2018", "coordinates": {"x": 536.5, "y": 520.0, "width": 86, "height": 17}}, {"label": "CASHIER", "coordinates": {"x": 57.5, "y": 562.0, "width": 61, "height": 17}}, {"label": "USER", "coordinates": {"x": 238.5, "y": 559.5, "width": 48, "height": 15}}, {"label": "TIME", "coordinates": {"x": 432.5, "y": 556.0, "width": 37, "height": 17}}, {"label": "12 31 00", "coordinates": {"x": 531.5, "y": 558.5, "width": 61, "height": 16}}, {"label": "SALESPERSON", "coordinates": {"x": 76.0, "y": 599.0, "width": 95, "height": 19}}, {"label": "REF.", "coordinates": {"x": 428.0, "y": 597.0, "width": 31, "height": 18}}, {"label": "ITEM", "coordinates": {"x": 46.5, "y": 666.0, "width": 33, "height": 15}}, {"label": "QTY", "coordinates": {"x": 268.5, "y": 665.5, "width": 27, "height": 20}}, {"label": "S/PRICE", "coordinates": {"x": 375.5, "y": 662.0, "width": 55, "height": 19}}, {"label": "AMOUNT", "coordinates": {"x": 502.0, "y": 664.5, "width": 65, "height": 15}}, {"label": "TAX", "coordinates": {"x": 611.0, "y": 665.0, "width": 28, "height": 16}}, {"label": "E8318", "coordinates": {"x": 55.5, "y": 701.0, "width": 48, "height": 16}}, {"label": "1", "coordinates": {"x": 269.0, "y": 694.5, "width": 22, "height": 18}}, {"label": "80.91", "coordinates": {"x": 377.0, "y": 697.5, "width": 52, "height": 18}}, {"label": "80.91", "coordinates": {"x": 518.0, "y": 697.0, "width": 52, "height": 23}}, {"label": "SR", "coordinates": {"x": 609.0, "y": 698.0, "width": 33, "height": 19}}, {"label": "ELEGANT SCHTR BAG 15", "coordinates": {"x": 136.5, "y": 737.0, "width": 210, "height": 16}}, {"label": "TOTAL QTY", "coordinates": {"x": 131.5, "y": 773.0, "width": 68, "height": 19}}, {"label": "1", "coordinates": {"x": 271.0, "y": 771.0, "width": 17, "height": 15}}, {"label": "80.91", "coordinates": {"x": 519.0, "y": 773.0, "width": 51, "height": 19}}, {"label": "TOTAL SALES (EXCLUDING GST) :", "coordinates": {"x": 210.5, "y": 827.0, "width": 223, "height": 16}}, {"label": "80.91", "coordinates": {"x": 521.5, "y": 827.0, "width": 41, "height": 16}}, {"label": "DISCOUNT :", "coordinates": {"x": 352.0, "y": 866.0, "width": 83, "height": 16}}, {"label": "0.00", "coordinates": {"x": 530.5, "y": 866.0, "width": 35, "height": 16}}, {"label": "TOTAL GST :", "coordinates": {"x": 343.0, "y": 907.0, "width": 92, "height": 17}}, {"label": "0.00", "coordinates": {"x": 528.5, "y": 906.5, "width": 49, "height": 22}}, {"label": "ROUNDING", "coordinates": {"x": 338.5, "y": 951.0, "width": 71, "height": 18}}, {"label": "-0.01", "coordinates": {"x": 526.0, "y": 949.0, "width": 53, "height": 20}}, {"label": "TOTAL SALES (INCLUSIVE OF GST) :", "coordinates": {"x": 178.0, "y": 996.0, "width": 257, "height": 18}}, {"label": "80.90", "coordinates": {"x": 522.5, "y": 990.0, "width": 52, "height": 21}}, {"label": "CASH :", "coordinates": {"x": 373.0, "y": 1039.5, "width": 65, "height": 18}}, {"label": "100.00", "coordinates": {"x": 514.5, "y": 1040.5, "width": 51, "height": 14}}, {"label": "CHANGE :", "coordinates": {"x": 356.0, "y": 1077.5, "width": 79, "height": 19}}, {"label": "19.10", "coordinates": {"x": 524.0, "y": 1077.5, "width": 43, "height": 16}}, {"label": "GST SUMMARY", "coordinates": {"x": 143.5, "y": 1151.0, "width": 137, "height": 16}}, {"label": "TAX CODE", "coordinates": {"x": 121.0, "y": 1197.5, "width": 77, "height": 16}}, {"label": "%", "coordinates": {"x": 268.0, "y": 1199.0, "width": 14, "height": 16}}, {"label": "AMT (RM)", "coordinates": {"x": 379.5, "y": 1198.5, "width": 75, "height": 18}}, {"label": "TAX (RM)", "coordinates": {"x": 536.5, "y": 1197.0, "width": 71, "height": 18}}, {"label": "SR", "coordinates": {"x": 95.0, "y": 1231.0, "width": 25, "height": 17}}, {"label": "0", "coordinates": {"x": 263.5, "y": 1228.5, "width": 23, "height": 18}}, {"label": "80.91", "coordinates": {"x": 408.5, "y": 1229.5, "width": 43, "height": 17}}, {"label": "0.00", "coordinates": {"x": 574.0, "y": 1229.5, "width": 35, "height": 14}}, {"label": "TOTAL :", "coordinates": {"x": 243.0, "y": 1274.5, "width": 66, "height": 26}}, {"label": "80.91", "coordinates": {"x": 406.5, "y": 1275.0, "width": 45, "height": 18}}, {"label": "0.00", "coordinates": {"x": 573.5, "y": 1278.5, "width": 34, "height": 16}}, {"label": "GOODS SOLD ARE NOT REFUNDABLE ONLY", "coordinates": {"x": 263.5, "y": 1349.5, "width": 314, "height": 14}}]}